BUGS
LICENSE
MANIFEST.in
QUICKSTART
README
TODO
setup.py
doc/gui.rst
doc/logging.rst
doc/triggers.rst
mudpyl/__init__.py
mudpyl/aliases.py
mudpyl/colours.py
mudpyl/escape_parser.py
mudpyl/matchers.py
mudpyl/metaline.py
mudpyl/modules.py
mudpyl/mudconnect.py
mudpyl/output_manager.py
mudpyl/realms.py
mudpyl/triggers.py
mudpyl.egg-info/PKG-INFO
mudpyl.egg-info/SOURCES.txt
mudpyl.egg-info/dependency_links.txt
mudpyl.egg-info/requires.txt
mudpyl.egg-info/top_level.txt
mudpyl/gui/__init__.py
mudpyl/gui/bindings.py
mudpyl/gui/commandhistory.py
mudpyl/gui/gtkcommandline.py
mudpyl/gui/gtkgui.py
mudpyl/gui/gtkoutput.py
mudpyl/gui/keychords.py
mudpyl/gui/tabcomplete.py
mudpyl/library/__init__.py
mudpyl/library/antitheft.py
mudpyl/library/balance.py
mudpyl/library/blankgagger.py
mudpyl/library/colourtells.py
mudpyl/library/general.py
mudpyl/library/harvester.py
mudpyl/library/html.py
mudpyl/library/refiller.py
mudpyl/library/rifttracker.py
mudpyl/library/targetting.py
mudpyl/library/imperian/__init__.py
mudpyl/library/imperian/autosipper.py
mudpyl/library/imperian/balance.py
mudpyl/net/__init__.py
mudpyl/net/mccp.py
mudpyl/net/nvt.py
mudpyl/net/telnet.py
