Metadata-Version: 1.0
Name: mudpyl
Version: 0.3
Summary: Python MUD client
Home-page: https://launchpad.net/mudpyl/
Author: Sam Pointon
Author-email: sampointon@gmail.com
License: GNU GPL v2 or later
Platform: UNKNOWN
Classifier: Development Status :: 3 - Alpha
Classifier: Intended Audience :: End Users/Desktop
Classifier: License :: OSI Approved :: GNU General Public License (GPL)
Classifier: Topic :: Communications :: Chat
Classifier: Topic :: Games/Entertainment :: Multi-User Dungeons (MUD)
Classifier: Topic :: Terminals :: Telnet
